Metadata-Version: 1.1
Name: pptx-downsizer
Version: 0.1.3
Summary: Tool for downsizing Microsoft PowerPoint pptx presentations.
Home-page: https://github.com/scholer/pptx-downsizer
Author: Rasmus Scholer Sorensen
Author-email: rasmusscholer@gmail.com
License: GNU General Public License v3 (GPLv3)
Download-URL: https://github.com/scholer/pptx-downsizer/tarball/0.1.3
Keywords: pptx,PowerPoint,compression,downsizing,file size reduction
Platform: UNKNOWN
Classifier: Development Status :: 4 - Beta
Classifier: Intended Audience :: Science/Research
Classifier: Intended Audience :: Education
Classifier: Intended Audience :: End Users/Desktop
Classifier: Intended Audience :: Healthcare Industry
Classifier: Topic :: Education
Classifier: Topic :: Scientific/Engineering
Classifier: Topic :: Office/Business
Classifier: Topic :: Office/Business :: Office Suites
Classifier: License :: OSI Approved :: GNU General Public License v3 (GPLv3)
Classifier: Programming Language :: Python
Classifier: Programming Language :: Python :: 3
Classifier: Programming Language :: Python :: 3.3
Classifier: Programming Language :: Python :: 3.4
Classifier: Programming Language :: Python :: 3.5
Classifier: Programming Language :: Python :: 3.6
Classifier: Environment :: Console
Classifier: Operating System :: MacOS
Classifier: Operating System :: Microsoft
Classifier: Operating System :: POSIX :: Linux
